django_admin_multiupload/__init__.py
django_admin_multiupload/apps.py
django_admin_multiupload/mixins.py
django_admin_multiupload/locale/af/LC_MESSAGES/django.mo
django_admin_multiupload/locale/af/LC_MESSAGES/django.po
django_admin_multiupload/locale/ar/LC_MESSAGES/django.mo
django_admin_multiupload/locale/ar/LC_MESSAGES/django.po
django_admin_multiupload/locale/az/LC_MESSAGES/django.mo
django_admin_multiupload/locale/az/LC_MESSAGES/django.po
django_admin_multiupload/locale/be/LC_MESSAGES/django.mo
django_admin_multiupload/locale/be/LC_MESSAGES/django.po
django_admin_multiupload/locale/bg/LC_MESSAGES/django.mo
django_admin_multiupload/locale/bg/LC_MESSAGES/django.po
django_admin_multiupload/locale/ca/LC_MESSAGES/django.mo
django_admin_multiupload/locale/ca/LC_MESSAGES/django.po
django_admin_multiupload/locale/cs/LC_MESSAGES/django.mo
django_admin_multiupload/locale/cs/LC_MESSAGES/django.po
django_admin_multiupload/locale/da/LC_MESSAGES/django.mo
django_admin_multiupload/locale/da/LC_MESSAGES/django.po
django_admin_multiupload/locale/de/LC_MESSAGES/django.mo
django_admin_multiupload/locale/de/LC_MESSAGES/django.po
django_admin_multiupload/locale/el/LC_MESSAGES/django.mo
django_admin_multiupload/locale/el/LC_MESSAGES/django.po
django_admin_multiupload/locale/en/LC_MESSAGES/django.mo
django_admin_multiupload/locale/en/LC_MESSAGES/django.po
django_admin_multiupload/locale/en-au/LC_MESSAGES/django.mo
django_admin_multiupload/locale/en-au/LC_MESSAGES/django.po
django_admin_multiupload/locale/en-gb/LC_MESSAGES/django.mo
django_admin_multiupload/locale/en-gb/LC_MESSAGES/django.po
django_admin_multiupload/locale/es/LC_MESSAGES/django.mo
django_admin_multiupload/locale/es/LC_MESSAGES/django.po
django_admin_multiupload/locale/es-ar/LC_MESSAGES/django.mo
django_admin_multiupload/locale/es-ar/LC_MESSAGES/django.po
django_admin_multiupload/locale/es-co/LC_MESSAGES/django.mo
django_admin_multiupload/locale/es-co/LC_MESSAGES/django.po
django_admin_multiupload-0.1.5.dist-info/licenses/LICENSE
django_admin_multiupload-0.1.5.dist-info/METADATA
django_admin_multiupload-0.1.5.dist-info/WHEEL
django_admin_multiupload-0.1.5.dist-info/top_level.txt
django_admin_multiupload-0.1.5.dist-info/RECORD
